ihoop/__init__.py
ihoop/strict.py
ihoop-0.1.1.dist-info/licenses/LICENSE
ihoop-0.1.1.dist-info/METADATA
ihoop-0.1.1.dist-info/WHEEL
ihoop-0.1.1.dist-info/top_level.txt
ihoop-0.1.1.dist-info/RECORD
