Metadata-Version: 2.4
Name: ihoop
Version: 0.1.1
Summary: Abstract/Final Patterns in Python
Author: lockwo
Project-URL: repository, https://github.com/lockwo/ihoop
Keywords: python,metaclasses,typing,concrete,strict
Classifier: Development Status :: 3 - Alpha
Classifier: Intended Audience :: Developers
Classifier: Natural Language :: English
Classifier: Programming Language :: Python :: 3
Requires-Python: >=3.9
License-File: LICENSE
Provides-Extra: examples
Requires-Dist: equinox>=0.13.0; extra == "examples"
Provides-Extra: testing
Requires-Dist: pytest==7.2.0; extra == "testing"
Requires-Dist: nbmake==1.4.3; extra == "testing"
Requires-Dist: ruff==0.11.0; extra == "testing"
Requires-Dist: pyright==1.1.398; extra == "testing"
Requires-Dist: setuptools>=61.0; extra == "testing"
Dynamic: license-file
